{
   "defense0Position" : "SpyBot",
   "startDefense" : "LowBar",
   "allianceColor" : "blue",
   "defense5Position" : "RoughTerrain",
   "matchNumber" : "147",
   "actions" : [
      {
         "Defend" : {
            "goal" : "highRight",
            "phase" : "teleop",
            "blockscore" : "score"
         }
      },
      {
         "Defend" : {
            "goal" : "lowRight",
            "phase" : "teleop",
            "blockscore" : "score"
         }
      },
      {
         "Defend" : {
            "goal" : "highLeft",
            "phase" : "teleop",
            "blockscore" : "score"
         }
      },
      {
         "Defend" : {
            "goal" : "lowLeft",
            "phase" : "teleop",
            "blockscore" : "score"
         }
      },
      {
         "Defend" : {
            "goal" : "highLeft",
            "phase" : "teleop",
            "blockscore" : "block"
         }
      },
      {
         "crossdefense" : {
            "direction" : "cross",
            "helped" : "false",
            "phase" : "teleop",
            "defense" : "1",
            "time" : 1300,
            "successfail" : "success"
         }
      },
      {
         "climb" : {
            "partOfBatter" : "center",
            "phase" : "teleop",
            "successfail" : "success"
         }
      }
   ],
   "defense1Position" : "LowBar",
   "withBall" : "true",
   "defense4Position" : "SallyPort",
   "defense3Position" : "Ramparts",
   "scouterName" : "Sean",
   "defense2Position" : "Portcullis",
   "teamNumber" : "16",
   "scouterNotes" : "These are notes!"
}
