{
   "defense0Position" : "SpyBot",
   "startDefense" : "RockWall",
   "allianceColor" : "red",
   "defense5Position" : "RockWall",
   "matchNumber" : "34",
   "actions" : [
      {
         "Defend" : {
            "goal" : "lowRight",
            "phase" : "teleop",
            "blockscore" : "score"
         }
      },
      {
         "Defend" : {
            "goal" : "highCenter",
            "phase" : "teleop",
            "blockscore" : "score"
         }
      },
      {
         "Defend" : {
            "goal" : "lowRight",
            "phase" : "teleop",
            "blockscore" : "block"
         }
      },
      {
         "Defend" : {
            "goal" : "highLeft",
            "phase" : "teleop",
            "blockscore" : "score"
         }
      },
      {
         "Defend" : {
            "goal" : "lowRight",
            "phase" : "teleop",
            "blockscore" : "score"
         }
      },
      {
         "Defend" : {
            "goal" : "lowRight",
            "phase" : "teleop",
            "blockscore" : "score"
         }
      }
   ],
   "defense1Position" : "LowBar",
   "withBall" : "true",
   "defense4Position" : "SallyPort",
   "defense3Position" : "Moat",
   "scouterName" : "William",
   "defense2Position" : "Cheval",
   "teamNumber" : "2",
   "scouterNotes" : ""
}
