{
   "defense0Position" : "SpyBot",
   "startDefense" : "LowBar",
   "allianceColor" : "red",
   "defense5Position" : "RoughTerrain",
   "matchNumber" : "65",
   "actions" : [
      {
         "crossdefense" : {
            "direction" : "cross",
            "helped" : "false",
            "phase" : "teleop",
            "defense" : "1",
            "time" : 1700,
            "successfail" : "success"
         }
      },
      {
         "crossdefense" : {
            "direction" : "back",
            "helped" : "false",
            "phase" : "teleop",
            "defense" : "1",
            "time" : 2000,
            "successfail" : "success"
         }
      },
      {
         "crossdefense" : {
            "direction" : "cross",
            "helped" : "false",
            "phase" : "teleop",
            "defense" : "1",
            "time" : 1600,
            "successfail" : "fail"
         }
      },
      {
         "crossdefense" : {
            "direction" : "back",
            "helped" : "false",
            "phase" : "teleop",
            "defense" : "1",
            "time" : 1500,
            "successfail" : "success"
         }
      },
      {
         "crossdefense" : {
            "direction" : "cross",
            "helped" : "false",
            "phase" : "teleop",
            "defense" : "1",
            "time" : 1200,
            "successfail" : "fail"
         }
      },
      {
         "crossdefense" : {
            "direction" : "back",
            "helped" : "false",
            "phase" : "teleop",
            "defense" : "1",
            "time" : 1900,
            "successfail" : "success"
         }
      },
      {
         "crossdefense" : {
            "direction" : "cross",
            "helped" : "false",
            "phase" : "teleop",
            "defense" : "3",
            "time" : 3200,
            "successfail" : "success"
         }
      },
      {
         "crossdefense" : {
            "direction" : "back",
            "helped" : "false",
            "phase" : "teleop",
            "defense" : "3",
            "time" : 4400,
            "successfail" : "success"
         }
      },
      {
         "crossdefense" : {
            "direction" : "cross",
            "helped" : "false",
            "phase" : "teleop",
            "defense" : "3",
            "time" : 4000,
            "successfail" : "success"
         }
      },
      {
         "crossdefense" : {
            "direction" : "back",
            "helped" : "false",
            "phase" : "teleop",
            "defense" : "3",
            "time" : 4900,
            "successfail" : "success"
         }
      },
      {
         "crossdefense" : {
            "direction" : "cross",
            "helped" : "false",
            "phase" : "teleop",
            "defense" : "5",
            "time" : 4500,
            "successfail" : "fail"
         }
      },
      {
         "crossdefense" : {
            "direction" : "back",
            "helped" : "false",
            "phase" : "teleop",
            "defense" : "5",
            "time" : 4200,
            "successfail" : "success"
         }
      },
      {
         "crossdefense" : {
            "direction" : "cross",
            "helped" : "false",
            "phase" : "teleop",
            "defense" : "5",
            "time" : 5300,
            "successfail" : "success"
         }
      },
      {
         "crossdefense" : {
            "direction" : "back",
            "helped" : "false",
            "phase" : "teleop",
            "defense" : "5",
            "time" : 4800,
            "successfail" : "success"
         }
      },
      {
         "crossdefense" : {
            "direction" : "cross",
            "helped" : "false",
            "phase" : "teleop",
            "defense" : "5",
            "time" : 3400,
            "successfail" : "fail"
         }
      },
      {
         "crossdefense" : {
            "direction" : "back",
            "helped" : "false",
            "phase" : "teleop",
            "defense" : "5",
            "time" : 4300,
            "successfail" : "success"
         }
      },
      {
         "crossdefense" : {
            "direction" : "cross",
            "helped" : "false",
            "phase" : "teleop",
            "defense" : "5",
            "time" : 6000,
            "successfail" : "success"
         }
      },
      {
         "crossdefense" : {
            "direction" : "cross",
            "helped" : "false",
            "phase" : "teleop",
            "defense" : "5",
            "time" : 3400,
            "successfail" : "fail"
         }
      },
      {
         "climb" : {
            "partOfBatter" : "right",
            "phase" : "teleop",
            "successfail" : "success"
         }
      }
   ],
   "defense1Position" : "LowBar",
   "withBall" : "true",
   "defense4Position" : "SallyPort",
   "defense3Position" : "Moat",
   "scouterName" : "Kobe",
   "defense2Position" : "Portcullis",
   "teamNumber" : "29",
   "scouterNotes" : ""
}
