{
   "defense0Position" : "SpyBot",
   "startDefense" : "RoughTerrain",
   "allianceColor" : "red",
   "defense5Position" : "RockWall",
   "matchNumber" : "64",
   "actions" : [
      {
         "crossdefense" : {
            "direction" : "cross",
            "helped" : "false",
            "phase" : "teleop",
            "defense" : "1",
            "time" : 1400,
            "successfail" : "success"
         }
      },
      {
         "crossdefense" : {
            "direction" : "back",
            "helped" : "false",
            "phase" : "teleop",
            "defense" : "1",
            "time" : 1400,
            "successfail" : "success"
         }
      },
      {
         "crossdefense" : {
            "direction" : "cross",
            "helped" : "false",
            "phase" : "teleop",
            "defense" : "1",
            "time" : 1500,
            "successfail" : "success"
         }
      },
      {
         "crossdefense" : {
            "direction" : "back",
            "helped" : "false",
            "phase" : "teleop",
            "defense" : "1",
            "time" : 1300,
            "successfail" : "success"
         }
      },
      {
         "crossdefense" : {
            "direction" : "back",
            "helped" : "false",
            "phase" : "teleop",
            "defense" : "1",
            "time" : 1600,
            "successfail" : "fail"
         }
      },
      {
         "crossdefense" : {
            "direction" : "cross",
            "helped" : "false",
            "phase" : "teleop",
            "defense" : "5",
            "time" : 3900,
            "successfail" : "success"
         }
      },
      {
         "crossdefense" : {
            "direction" : "back",
            "helped" : "false",
            "phase" : "teleop",
            "defense" : "5",
            "time" : 3700,
            "successfail" : "fail"
         }
      },
      {
         "crossdefense" : {
            "direction" : "cross",
            "helped" : "false",
            "phase" : "teleop",
            "defense" : "5",
            "time" : 4000,
            "successfail" : "success"
         }
      },
      {
         "crossdefense" : {
            "direction" : "back",
            "helped" : "false",
            "phase" : "teleop",
            "defense" : "5",
            "time" : 3800,
            "successfail" : "fail"
         }
      },
      {
         "crossdefense" : {
            "direction" : "cross",
            "helped" : "false",
            "phase" : "teleop",
            "defense" : "3",
            "time" : 4400,
            "successfail" : "success"
         }
      },
      {
         "crossdefense" : {
            "direction" : "back",
            "helped" : "false",
            "phase" : "teleop",
            "defense" : "1",
            "time" : 1500,
            "successfail" : "success"
         }
      },
      {
         "crossdefense" : {
            "direction" : "back",
            "helped" : "false",
            "phase" : "teleop",
            "defense" : "1",
            "time" : 1700,
            "successfail" : "fail"
         }
      },
      {
         "crossdefense" : {
            "direction" : "cross",
            "helped" : "false",
            "phase" : "teleop",
            "defense" : "3",
            "time" : 6700,
            "successfail" : "fail"
         }
      },
      {
         "crossdefense" : {
            "direction" : "back",
            "helped" : "false",
            "phase" : "teleop",
            "defense" : "1",
            "time" : 1800,
            "successfail" : "success"
         }
      },
      {
         "crossdefense" : {
            "direction" : "cross",
            "helped" : "false",
            "phase" : "teleop",
            "defense" : "3",
            "time" : 4600,
            "successfail" : "success"
         }
      },
      {
         "crossdefense" : {
            "direction" : "back",
            "helped" : "false",
            "phase" : "teleop",
            "defense" : "1",
            "time" : 1600,
            "successfail" : "success"
         }
      },
      {
         "crossdefense" : {
            "direction" : "cross",
            "helped" : "false",
            "phase" : "teleop",
            "defense" : "2",
            "time" : 7800,
            "successfail" : "success"
         }
      },
      {
         "crossdefense" : {
            "direction" : "back",
            "helped" : "false",
            "phase" : "teleop",
            "defense" : "1",
            "time" : 1100,
            "successfail" : "success"
         }
      },
      {
         "crossdefense" : {
            "direction" : "cross",
            "helped" : "false",
            "phase" : "teleop",
            "defense" : "2",
            "time" : 7200,
            "successfail" : "success"
         }
      },
      {
         "challenge" : {
            "partOfBatter" : "left",
            "phase" : "teleop",
            "successfail" : "success"
         }
      }
   ],
   "defense1Position" : "LowBar",
   "withBall" : "true",
   "defense4Position" : "SallyPort",
   "defense3Position" : "Moat",
   "scouterName" : "Chris",
   "defense2Position" : "Cheval",
   "teamNumber" : "37",
   "scouterNotes" : "These are notes!"
}
