{
   "defense0Position" : "SpyBot",
   "startDefense" : "Moat",
   "allianceColor" : "red",
   "defense5Position" : "RockWall",
   "matchNumber" : "6",
   "actions" : [
      {
         "Defend" : {
            "goal" : "lowRight",
            "phase" : "teleop",
            "blockscore" : "score"
         }
      },
      {
         "Defend" : {
            "goal" : "highCenter",
            "phase" : "teleop",
            "blockscore" : "score"
         }
      },
      {
         "Defend" : {
            "goal" : "lowRight",
            "phase" : "teleop",
            "blockscore" : "score"
         }
      },
      {
         "Defend" : {
            "goal" : "highCenter",
            "phase" : "teleop",
            "blockscore" : "score"
         }
      },
      {
         "Defend" : {
            "goal" : "highCenter",
            "phase" : "teleop",
            "blockscore" : "block"
         }
      },
      {
         "Defend" : {
            "goal" : "highRight",
            "phase" : "teleop",
            "blockscore" : "score"
         }
      },
      {
         "crossdefense" : {
            "direction" : "cross",
            "helped" : "false",
            "phase" : "teleop",
            "defense" : "1",
            "time" : 2900,
            "successfail" : "success"
         }
      },
      {
         "challenge" : {
            "partOfBatter" : "center",
            "phase" : "teleop",
            "successfail" : "success"
         }
      }
   ],
   "defense1Position" : "LowBar",
   "withBall" : "true",
   "defense4Position" : "SallyPort",
   "defense3Position" : "Moat",
   "scouterName" : "Chris",
   "defense2Position" : "Portcullis",
   "teamNumber" : "50",
   "scouterNotes" : "These are notes!"
}
